rustic_ai/vertexai/__init__.py
rustic_ai/vertexai/agent_ext/__init__.py
rustic_ai/vertexai/agent_ext/embeddings.py
rustic_ai/vertexai/agents/__init__.py
rustic_ai/vertexai/agents/content_moderation.py
rustic_ai/vertexai/agents/google_research_agent.py
rustic_ai/vertexai/agents/image_generation.py
rustic_ai/vertexai/client.py
rusticai_vertexai-1.0.0.dist-info/METADATA
rusticai_vertexai-1.0.0.dist-info/WHEEL
rusticai_vertexai-1.0.0.dist-info/RECORD
