Metadata-Version: 2.4
Name: rusticai-vertexai
Version: 1.0.0
Summary: Rustic AI module with Vertex AI integrations
License-Expression: Apache-2.0
Author: Dragonscale Industries Inc.
Author-email: dev@dragonscale.ai
Requires-Python: >=3.12,<3.13
Classifier: Programming Language :: Python :: 3
Classifier: Programming Language :: Python :: 3.12
Provides-Extra: test
Requires-Dist: google-cloud-aiplatform (>=1.91.0,<2.0.0)
Requires-Dist: google-cloud-language (>=2.17.2,<3.0.0)
Requires-Dist: google-genai (>=1.24.0,<2.0.0)
Requires-Dist: rusticai-core (>=1.0.0,<1.1.0)
Requires-Dist: tabulate (>=0.9.0,<0.10.0)
Project-URL: Homepage, https://www.rustic.ai/
Project-URL: Repository, https://github.com/rustic-ai/rustic-ai
Project-URL: Rustic AI Core, https://pypi.org/project/rusticai-core/
